MANIFEST.in
README.rst
setup.cfg
setup.py
versioneer.py
scikit_surgeryfredbackend.egg-info/PKG-INFO
scikit_surgeryfredbackend.egg-info/SOURCES.txt
scikit_surgeryfredbackend.egg-info/dependency_links.txt
scikit_surgeryfredbackend.egg-info/requires.txt
scikit_surgeryfredbackend.egg-info/top_level.txt
sksurgeryfredbe/__init__.py
sksurgeryfredbe/_version.py
sksurgeryfredbe/algorithms/__init__.py
sksurgeryfredbe/algorithms/ablation.py
sksurgeryfredbe/algorithms/errors.py
sksurgeryfredbe/algorithms/fit_contour.py
sksurgeryfredbe/algorithms/fle.py
sksurgeryfredbe/algorithms/fred.py
sksurgeryfredbe/algorithms/point_based_reg.py
sksurgeryfredbe/algorithms/scores.py
sksurgeryfredbe/logging/__init__.py
sksurgeryfredbe/logging/fred_logger.py
tests/algorithms/__init__.py
tests/algorithms/test_errors.py
tests/algorithms/test_fle.py
tests/algorithms/test_pbr.py
tests/algorithms/test_scores.py
tests/logging/__init__.py
tests/logging/test_logger.py